<package>
  <description brief="euslisp">

     euslisp and irteus

  </description>
  <author>Toshihiro Matsui and JSK, ROS maintained by Kei Okada</author>
  <license>BSD</license>
  <review status="unreviewed" notes=""/>
  <url>http://ros.org/wiki/euslisp</url>

  <export>
    <cpp cflags="-I${prefix}/eus/include" />
    <rosdoc config="rosdoc.yaml" />
  </export>

  <rosdep name="git" />
  <rosdep name="rosbuild" />
  <rosdep name="opengl" />
  <rosdep name="libjpeg" />
  <rosdep name="libx11-dev" />
  <rosdep name="libxext" />
  <rosdep name="libpng12-dev" />
  <rosdep name="libpq-dev" />
  <rosdep name="mk" />
  <rosdep name="xfonts-100dpi" />
  <rosdep name="xfonts-75dpi" />
  <rosdep name="xfont-server" />

  <rosdep name="rostest" />
  <!-- rosdep name="ttf-mscorefonts-installer" / -->
</package>


